{
   "author" : "Maroš Kollár",
   "category" : "scheduling",
   "defaults" : {
      "description" : "__description__",
      "title" : "__title__"
   },
   "dependencies" : [],
   "homepage" : "http://k-1.com",
   "icon" : "presence_on.png",
   "maturity" : "stable",
   "moduleName" : "Presence",
   "options" : {
      "fields" : {
         "night_end" : {
            "label" : "__night_end_label__",
            "maskString" : "99:99",
            "placeholder" : "__time_placeholder__",
            "type" : "time",
            "order": 2
         },
         "night_start" : {
            "label" : "__night_start_label__",
            "maskString" : "99:99",
            "placeholder" : "__time_placeholder__",
            "type" : "time",
            "order": 1
         }
      }
   },
   "repository" : {
      "source" : "https://github.com/maros/Zway-Presence",
      "type" : "git"
   },
   "schema" : {
      "properties" : {
         "night_end" : {
            "pattern" : "^(([01]?[0-9]|(2[0-3])):([0-5][0-9])$",
            "required" : true,
            "type" : "string"
         },
         "night_start" : {
            "pattern" : "^(([01]?[0-9]|(2[0-3])):([0-5][0-9])$",
            "required" : true,
            "type" : "string"
         }
      },
      "required" : true,
      "type" : "object"
   },
   "singleton" : true,
   "version" : "1.01"
}
